{
  "url" : "https://github.com/matteobaccan/html2pop3/pull/626",
  "project" : "html2pop3",
  "projectOrganisation" : "matteobaccan",
  "breakingCommit" : "094acd0dca9978c631bae0ae17ab992a5b129192",
  "prAuthor" : "bot",
  "preCommitAuthor" : "bot",
  "breakingCommitAuthor" : "bot",
  "updatedDependency" : {
    "dependencyGroupID" : "org.jsoup",
    "dependencyArtifactID" : "jsoup",
    "previousVersion" : "1.18.1",
    "newVersion" : "1.18.2",
    "dependencyScope" : "compile",
    "versionUpdateType" : "patch",
    "dependencySection" : "dependencies"
  },
  "licenseInfo" : "GNU General Public License v3.0"
}