{
  "url" : "https://github.com/apache/plc4x-extras/pull/340",
  "project" : "plc4x-extras",
  "projectOrganisation" : "apache",
  "breakingCommit" : "09f6f3de6843e6e1e22c1d9df9c4b5147a889c14",
  "prAuthor" : "bot",
  "preCommitAuthor" : "human",
  "breakingCommitAuthor" : "bot",
  "updatedDependency" : {
    "dependencyGroupID" : "io.netty",
    "dependencyArtifactID" : "netty-transport",
    "previousVersion" : "4.1.119.Final",
    "newVersion" : "4.2.1.Final",
    "dependencyScope" : "compile",
    "versionUpdateType" : "other",
    "dependencySection" : "dependencies"
  },
  "licenseInfo" : "unknown"
}