{
  "url" : "https://github.com/Axway-API-Management-Plus/apim-cli/pull/502",
  "project" : "apim-cli",
  "projectOrganisation" : "Axway-API-Management-Plus",
  "breakingCommit" : "4ecfd5d5cc8dd81c12e1194fe2f3f51994d366b6",
  "prAuthor" : "bot",
  "preCommitAuthor" : "unknown",
  "breakingCommitAuthor" : "bot",
  "updatedDependency" : {
    "dependencyGroupID" : "commons-io",
    "dependencyArtifactID" : "commons-io",
    "previousVersion" : "2.11.0",
    "newVersion" : "2.14.0",
    "dependencyScope" : "compile",
    "versionUpdateType" : "minor",
    "dependencySection" : "dependencyManagement"
  },
  "licenseInfo" : "Apache License 2.0"
}