{
  "url" : "https://github.com/hoangtien2k3/reactify-core/pull/45",
  "project" : "reactify-core",
  "projectOrganisation" : "hoangtien2k3",
  "breakingCommit" : "634576a15d5e4399212fd986bca8596b2618ce25",
  "prAuthor" : "bot",
  "preCommitAuthor" : "human",
  "breakingCommitAuthor" : "bot",
  "updatedDependency" : {
    "dependencyGroupID" : "org.springframework.boot",
    "dependencyArtifactID" : "spring-boot-starter-web",
    "previousVersion" : "3.3.5",
    "newVersion" : "3.4.1",
    "dependencyScope" : "compile",
    "versionUpdateType" : "minor",
    "dependencySection" : "dependencies"
  },
  "licenseInfo" : "Apache License 2.0"
}