{
  "url" : "https://github.com/jenkinsci/tekton-client-plugin/pull/400",
  "project" : "tekton-client-plugin",
  "projectOrganisation" : "jenkinsci",
  "breakingCommit" : "8569e1be156aa516c009a58042127c3f64c9a89f",
  "prAuthor" : "bot",
  "preCommitAuthor" : "human",
  "breakingCommitAuthor" : "human",
  "updatedDependency" : {
    "dependencyGroupID" : "com.fasterxml.jackson.module",
    "dependencyArtifactID" : "jackson-module-jaxb-annotations",
    "previousVersion" : "2.19.0",
    "newVersion" : "2.19.1",
    "dependencyScope" : "compile",
    "versionUpdateType" : "patch",
    "dependencySection" : "dependencyManagement"
  },
  "licenseInfo" : "Apache License 2.0"
}