{
  "url" : "https://github.com/ChanceSD/PvPManager/pull/584",
  "project" : "PvPManager",
  "projectOrganisation" : "ChanceSD",
  "breakingCommit" : "af1f2af979423a019e6e3b78ffb66eddc23bde00",
  "prAuthor" : "bot",
  "preCommitAuthor" : "human",
  "breakingCommitAuthor" : "bot",
  "updatedDependency" : {
    "dependencyGroupID" : "net.william278.huskclaims",
    "dependencyArtifactID" : "huskclaims-bukkit",
    "previousVersion" : "1.5.2",
    "newVersion" : "1.5.8",
    "dependencyScope" : "provided",
    "versionUpdateType" : "patch",
    "dependencySection" : "dependencies"
  },
  "licenseInfo" : "Other"
}