{
  "url" : "https://github.com/FluentLenium/FluentLenium/pull/2204",
  "project" : "FluentLenium",
  "projectOrganisation" : "FluentLenium",
  "breakingCommit" : "c5c6c16157d41f5a4174f174bf70da868402a87d",
  "prAuthor" : "bot",
  "preCommitAuthor" : "human",
  "breakingCommitAuthor" : "bot",
  "updatedDependency" : {
    "dependencyGroupID" : "org.mockito",
    "dependencyArtifactID" : "mockito-junit-jupiter",
    "previousVersion" : "5.11.0",
    "newVersion" : "5.15.2",
    "dependencyScope" : "compile",
    "versionUpdateType" : "minor",
    "dependencySection" : "dependencyManagement"
  },
  "licenseInfo" : "Other"
}