{
  "url" : "https://github.com/hoangtien2k3/reactify-core/pull/80",
  "project" : "reactify-core",
  "projectOrganisation" : "hoangtien2k3",
  "breakingCommit" : "e703b9943699c2ec0c9b372dd64b6593852650ac",
  "prAuthor" : "bot",
  "preCommitAuthor" : "human",
  "breakingCommitAuthor" : "bot",
  "updatedDependency" : {
    "dependencyGroupID" : "com.github.ben-manes.caffeine",
    "dependencyArtifactID" : "caffeine",
    "previousVersion" : "3.1.8",
    "newVersion" : "3.2.0",
    "dependencyScope" : "compile",
    "versionUpdateType" : "minor",
    "dependencySection" : "dependencies"
  },
  "licenseInfo" : "Apache License 2.0"
}