{
  "url" : "https://github.com/jenkinsci/htmlpublisher-plugin/pull/356",
  "project" : "htmlpublisher-plugin",
  "projectOrganisation" : "jenkinsci",
  "breakingCommit" : "fc5102004aad3d936a6d030c29643b9ebb24cc65",
  "prAuthor" : "bot",
  "preCommitAuthor" : "human",
  "breakingCommitAuthor" : "bot",
  "updatedDependency" : {
    "dependencyGroupID" : "io.jenkins.tools.bom",
    "dependencyArtifactID" : "bom-${jenkins.baseline}.x",
    "previousVersion" : "4051.v78dce3ce8b_d6",
    "newVersion" : "4845.v9163d3278e4f",
    "dependencyScope" : "import",
    "versionUpdateType" : "other",
    "dependencySection" : "dependencyManagement"
  },
  "licenseInfo" : "MIT License"
}